forevervm_sdk/__init__.py
forevervm_sdk/config.py
forevervm_sdk/repl.py
forevervm_sdk/types.py
forevervm_sdk-0.1.35.dist-info/METADATA
forevervm_sdk-0.1.35.dist-info/WHEEL
forevervm_sdk-0.1.35.dist-info/RECORD
