Metadata-Version: 2.4
Name: forevervm-sdk
Version: 0.1.35
Summary: Developer SDK for foreverVM
Requires-Dist: httpx-ws>=0.7.1
Requires-Dist: httpx>=0.28.1
